imagetensors/__init__.py
imagetensors/base.py
imagetensors/converters.py
imagetensors/factory.py
imagetensors/models.py
imagetensors/readers/__init__.py
imagetensors/readers/_czi_metadata.py
imagetensors/readers/czi.py
imagetensors/readers/lif.py
imagetensors/readers/nd.py
imagetensors/readers/oib.py
imagetensors/readers/tif.py
imagetensors-0.2.1.dist-info/WHEEL
imagetensors-0.2.1.dist-info/METADATA
imagetensors-0.2.1.dist-info/RECORD
