Metadata-Version: 2.3
Name: imagetensors
Version: 0.2.1
Summary: imagetensors provides a standardized, unified interface for reading multiple proprietary microscopy image formats, converting them into standardized 5D NumPy arrays (T, Z, C, Y, X) for seamless downstream analysis and processing.
Requires-Dist: czifile>=2019.7.2.1
Requires-Dist: czitools>=0.11.1
Requires-Dist: oiffile>=2025.5.10
Requires-Dist: readlif>=0.6.6
Requires-Dist: tifffile>=2025.10.16
Requires-Python: >=3.12
